{
  "timestamp": "/Users/Branden/branden/Project_Chimera_v3.0_Phoenix/AI_Server",
  "confidence": 100,
  "components": {
    "engine_mapping": {
      "status": "\u2705",
      "issues": []
    },
    "trinity_context": {
      "status": "\u2705",
      "issues": []
    },
    "preset_corpus": {
      "status": "\u2705",
      "issues": []
    },
    "smart_components": {
      "status": "\u2705",
      "issues": []
    },
    "pipeline": {
      "status": "\u2705",
      "issues": [
        "Optional visionary.py not found"
      ]
    }
  },
  "summary": {
    "passed": 5,
    "warnings": 0,
    "errors": 0
  }
}